CHANGES.txt
LICENSE.txt
MANIFEST.in
README.rst
setup.cfg
setup.py
bin/salvus
salvus/README.rst
salvus/__init__.py
salvus/__main__.py
salvus/server.py
salvus.egg-info/PKG-INFO
salvus.egg-info/SOURCES.txt
salvus.egg-info/dependency_links.txt
salvus.egg-info/requires.txt
salvus.egg-info/top_level.txt